hicli/__init__.py
hicli/__main__.py
hicli/actions.py
hicli/cli.py
hicli/exceptions.py
hicli/group.py
hicli/host.py
hicli/log.py
hicli/rules.py
hicli-2.0.0.dist-info/LICENSE
hicli-2.0.0.dist-info/METADATA
hicli-2.0.0.dist-info/WHEEL
hicli-2.0.0.dist-info/entry_points.txt
hicli-2.0.0.dist-info/top_level.txt
hicli-2.0.0.dist-info/RECORD
